HISTORY.md
LICENSE
MANIFEST.in
README.md
requirements.txt
setup.py
app_defaults/__init__.py
app_defaults/defaults.py
django_app_defaults.egg-info/PKG-INFO
django_app_defaults.egg-info/SOURCES.txt
django_app_defaults.egg-info/dependency_links.txt
django_app_defaults.egg-info/not-zip-safe
django_app_defaults.egg-info/top_level.txt