Metadata-Version: 1.1
Name: django-app-defaults
Version: 1.1
Summary: A library for managing apps and projects default static settings.
Home-page: https://github.com/nitely/django-app-defaults
Author: Esteban Castro Borsani
Author-email: ecastroborsani@gmail.com
License: MIT License
Platform: UNKNOWN
Classifier: Development Status :: 5 - Production/Stable
Classifier: Environment :: Web Environment
Classifier: Framework :: Django
Classifier: Intended Audience :: Developers
Classifier: License :: OSI Approved :: MIT License
Classifier: Operating System :: OS Independent
Classifier: Programming Language :: Python
Classifier: Programming Language :: Python :: 2
Classifier: Programming Language :: Python :: 3
Classifier: Topic :: Internet :: WWW/HTTP
Classifier: Topic :: Internet :: WWW/HTTP :: Dynamic Content
